globalframework/__init__.py
globalframework/celery_app.py
globalframework/constants.py
globalframework/enumeration.py
globalframework/error_dict.py
globalframework/errors.py
globalframework/health_check.py
globalframework/caching/__init__.py
globalframework/caching/cache_manager.py
globalframework/data/ConfigurationSearchPath.json
globalframework/data/__init__.py
globalframework/data/adapter.py
globalframework/data/base.py
globalframework/data/baseprovider.py
globalframework/data/cloud_factory.py
globalframework/data/database_factory.py
globalframework/data/modal.py
globalframework/data/odbc_connection.py
globalframework/data/psycopg_connection.py
globalframework/data/query.py
globalframework/data/setting.py
globalframework/filter/__init__.py
globalframework/filter/manager.py
globalframework/filter/provider.py
globalframework/http/__init__.py
globalframework/http/base.py
globalframework/http/modal.py
globalframework/internationalisation/__init__.py
globalframework/internationalisation/manager.py
globalframework/internationalisation/provider.py
globalframework/logger/__init__.py
globalframework/logger/log.py
globalframework/logger/provider.py
globalframework/logger/queue_log.py
globalframework/mail/__init__.py
globalframework/mail/mailer.py
globalframework/mail/queue_mailer.py
globalframework/mail/backends/__init__.py
globalframework/mail/backends/base.py
globalframework/mail/backends/loc_mem.py
globalframework/mail/backends/smtp.py
globalframework/security/__init__.py
globalframework/security/authentication.py
globalframework/security/data_sanitizer.py
globalframework/security/encrypto.py
globalframework/security/encrypto_json.py
globalframework/security/input_stats.py
globalframework/security/manager.py
globalframework/security/model.py
globalframework/security/password_policy.py
globalframework/security/provider.py
globalframework/utility/__init__.py
globalframework/utility/bitwise_logic.py
globalframework/utility/utils.py
globalframework/validation/__init__.py
globalframework-1.0.2013.5.dist-info/METADATA
globalframework-1.0.2013.5.dist-info/WHEEL
globalframework-1.0.2013.5.dist-info/top_level.txt
globalframework-1.0.2013.5.dist-info/RECORD
